README.md
setup.cfg
setup.py
neuro_analysis_py.egg-info/PKG-INFO
neuro_analysis_py.egg-info/SOURCES.txt
neuro_analysis_py.egg-info/dependency_links.txt
neuro_analysis_py.egg-info/requires.txt
neuro_analysis_py.egg-info/top_level.txt
neuro_py/__init__.py